config/__init__.py
config/load_env.py
config/util.py
loggers/__init__.py
loggers/aws_logger.py
loggers/base_logger.py
loggers/gcp_logger.py
loggers/local_logger.py
techv_logger/__init__.py
techv_logger/logger_factory.py
techv_cloud_logger-0.1.3.dist-info/METADATA
techv_cloud_logger-0.1.3.dist-info/WHEEL
techv_cloud_logger-0.1.3.dist-info/top_level.txt
techv_cloud_logger-0.1.3.dist-info/RECORD
